hyqerionmath/__init__.py
hyqerionmath/factorization.py
hyqerionmath/primality.py
hyqerionmath/sequences.py
hyqerionmath-0.4.0.dist-info/licenses/LICENSE
hyqerionmath-0.4.0.dist-info/METADATA
hyqerionmath-0.4.0.dist-info/WHEEL
hyqerionmath-0.4.0.dist-info/top_level.txt
hyqerionmath-0.4.0.dist-info/RECORD
