Metadata-Version: 2.4
Name: hyqerionmath
Version: 0.4.0
Summary: A Python library with mathematical utilities: primality testing, prime generation, factorization, and Fibonacci sequence functions.
Author-email: Hyqerion <hyqerion199@gmail.com>
License: MIT License
Keywords: math,prime,primality,primes,nth prime,factor,factorization,prime factors,fibonacci,sequence,hyqerion,utilities,number theory
Classifier: Programming Language :: Python :: 3
Classifier: Programming Language :: Python :: 3.7
Classifier: Programming Language :: Python :: 3.8
Classifier: Programming Language :: Python :: 3.9
Classifier: Programming Language :: Python :: 3.10
Classifier: Programming Language :: Python :: 3.11
Classifier: Programming Language :: Python :: 3.12
Classifier: License :: OSI Approved :: MIT License
Classifier: Operating System :: OS Independent
Classifier: Intended Audience :: Developers
Classifier: Topic :: Scientific/Engineering :: Mathematics
Classifier: Development Status :: 3 - Alpha
Requires-Python: >=3.7
License-File: LICENSE
Dynamic: license-file
